armour365/__init__.py
armour365/authenticate.py
armour365/disenroll.py
armour365/enroll.py
armour365/log_config/__init__.py
armour365/log_config/logger.py
armour365/utils/__init__.py
gnani_voicebiometric_api/__init__.py
gnani_voicebiometric_api/authenticate.py
gnani_voicebiometric_api/disenroll.py
gnani_voicebiometric_api/enroll.py
gnani_voicebiometric_api/log_config/__init__.py
gnani_voicebiometric_api/log_config/logger.py
gnani_voicebiometric_api/utils/__init__.py
armour365-1.0.dist-info/METADATA
armour365-1.0.dist-info/WHEEL
armour365-1.0.dist-info/top_level.txt
armour365-1.0.dist-info/RECORD
