Metadata-Version: 2.1
Name: armour365
Version: 1.0
Summary: armour365
Home-page: UNKNOWN
Author: gnani.ai
Author-email: <api.service@gnani.ai>
License: UNKNOWN
Keywords: python,Voicebiometric service
Platform: UNKNOWN
Classifier: Development Status :: 3 - Alpha
Classifier: Intended Audience :: Education
Classifier: Programming Language :: Python :: 2
Classifier: Programming Language :: Python :: 3
Classifier: Operating System :: MacOS :: MacOS X
Classifier: Operating System :: Microsoft :: Windows
Requires-Dist: pytz
Requires-Dist: requests
